grains/__init__.py
grains/analysis.py
grains/cli.py
grains/errors.py
grains/graphics.py
grains/main.py
grains-0.1.0.dist-info/LICENSE
grains-0.1.0.dist-info/METADATA
grains-0.1.0.dist-info/WHEEL
grains-0.1.0.dist-info/entry_points.txt
grains-0.1.0.dist-info/top_level.txt
grains-0.1.0.dist-info/RECORD
