Metadata-Version: 2.1
Name: grains
Version: 0.1.0
Summary: UNKNOWN
Home-page: https://github.com/seatonullberg/grains
Author: Seaton Ullberg
Author-email: sullberg@ufl.edu
License: UNKNOWN
Platform: UNKNOWN
Requires-Dist: Click
